typehintjson/__init__.py
typehintjson/_impl.py
typehintjson/example.py
typehintjson-1.0.4.dist-info/METADATA
typehintjson-1.0.4.dist-info/WHEEL
typehintjson-1.0.4.dist-info/top_level.txt
typehintjson-1.0.4.dist-info/RECORD
