Metadata-Version: 2.1
Name: typehintjson
Version: 1.0.4
Summary: Converts dataclasses / enums to JSON and back using type hints
Home-page: https://github.com/Sanjay-Ganeshan/typehintjson
Author: Julie Ganeshan
Author-email: HeavenlyQueen@outlook.com
License: UNKNOWN
Platform: UNKNOWN
Classifier: Programming Language :: Python :: 3
Classifier: License :: OSI Approved :: MIT License
Classifier: Operating System :: OS Independent
Requires-Python: >=3.8
